LICENSE
MANIFEST.in
readme.rst
setup.py
magpysv/__init__.py
magpysv/baseline_records
magpysv/denoise.py
magpysv/io.py
magpysv/model_prediction.py
magpysv/plots.py
magpysv/tools.py
magpysv.egg-info/PKG-INFO
magpysv.egg-info/SOURCES.txt
magpysv.egg-info/dependency_links.txt
magpysv.egg-info/not-zip-safe
magpysv.egg-info/requires.txt
magpysv.egg-info/top_level.txt
magpysv/tests/__init__.py
magpysv/tests/test_io.py
magpysv/tests/test_tools.py