Metadata-Version: 1.1
Name: magpysv
Version: 1.0
Summary: Download, process and denoise geomagnetic observatory data
Home-page: https://github.com/gracecox/MagPySV
Author: Grace Cox
Author-email: grace.cox@dias.ie
License: MIT
Platform: UNKNOWN
Classifier: Programming Language :: Python :: 3
